twat_fs/__init__.py
twat_fs/__main__.py
twat_fs/__version__.py
twat_fs/cli.py
twat_fs/paths.py
twat_fs/py.typed
twat_fs/upload.py
twat_fs/data/_test.jpg
twat_fs/data/test.jpg
twat_fs/upload_providers/__init__.py
twat_fs/upload_providers/async_utils.py
twat_fs/upload_providers/bashupload.py
twat_fs/upload_providers/catbox.py
twat_fs/upload_providers/core.py
twat_fs/upload_providers/dropbox.py
twat_fs/upload_providers/factory.py
twat_fs/upload_providers/fal.py
twat_fs/upload_providers/filebin.py
twat_fs/upload_providers/litterbox.py
twat_fs/upload_providers/pixeldrain.py
twat_fs/upload_providers/protocols.py
twat_fs/upload_providers/s3.py
twat_fs/upload_providers/simple.py
twat_fs/upload_providers/types.py
twat_fs/upload_providers/uguu.py
twat_fs/upload_providers/utils.py
twat_fs/upload_providers/www0x0.py
twat_fs-2.7.5.dist-info/METADATA
twat_fs-2.7.5.dist-info/WHEEL
twat_fs-2.7.5.dist-info/entry_points.txt
twat_fs-2.7.5.dist-info/licenses/LICENSE
twat_fs-2.7.5.dist-info/RECORD
