Metadata-Version: 2.4
Name: twat-fs
Version: 2.7.5
Summary: File system utilities for twat with support for multiple upload providers
Project-URL: Documentation, https://github.com/twardoch/twat-fs#readme
Project-URL: Issues, https://github.com/twardoch/twat-fs/issues
Project-URL: Source, https://github.com/twardoch/twat-fs
Author-email: Adam Twardoch <adam+github@twardoch.com>
License-Expression: MIT
License-File: LICENSE
Keywords: dropbox,fal,file-upload,s3,twat
Classifier: Development Status :: 4 - Beta
Classifier: Programming Language :: Python
Classifier: Programming Language :: Python :: 3.10
Classifier: Programming Language :: Python :: 3.11
Classifier: Programming Language :: Python :: 3.12
Classifier: Programming Language :: Python :: Implementation :: CPython
Classifier: Programming Language :: Python :: Implementation :: PyPy
Requires-Python: >=3.10
Requires-Dist: aiohappyeyeballs>=2.5.0
Requires-Dist: aiohttp>=3.11.13
Requires-Dist: aiosignal>=1.3.2
Requires-Dist: attrs>=25.1.0
Requires-Dist: fire>=0.6.0
Requires-Dist: frozenlist>=1.5.0
Requires-Dist: loguru>=0.7.3
Requires-Dist: multidict>=6.1.0
Requires-Dist: propcache>=0.3.0
Requires-Dist: requests>=2.32.3
Requires-Dist: responses>=0.25.6
Requires-Dist: tenacity>=9.0.0
Requires-Dist: twat>=2.7.0
Requires-Dist: yarl>=1.18.3
Provides-Extra: all
Requires-Dist: aiohappyeyeballs>=2.4.6; extra == 'all'
Requires-Dist: aiohttp>=3.11.12; extra == 'all'
Requires-Dist: aiosignal>=1.3.2; extra == 'all'
Requires-Dist: attrs>=25.1.0; extra == 'all'
Requires-Dist: boto3>=1.36.22; extra == 'all'
Requires-Dist: botocore>=1.36.22; extra == 'all'
Requires-Dist: dropbox>=12.0.2; extra == 'all'
Requires-Dist: fal-client>=0.5.9; extra == 'all'
Requires-Dist: fire>=0.6.0; extra == 'all'
Requires-Dist: frozenlist>=1.5.0; extra == 'all'
Requires-Dist: loguru>=0.7.2; extra == 'all'
Requires-Dist: multidict>=6.1.0; extra == 'all'
Requires-Dist: propcache>=0.2.1; extra == 'all'
Requires-Dist: requests>=2.31.0; extra == 'all'
Requires-Dist: tenacity>=9.0.0; extra == 'all'
Requires-Dist: twat>=1.8.1; extra == 'all'
Requires-Dist: yarl>=1.18.3; extra == 'all'
Provides-Extra: dev
Requires-Dist: argparse-types; extra == 'dev'
Requires-Dist: botocore-stubs<=1.36.22; extra == 'dev'
Requires-Dist: botocore-types; extra == 'dev'
Requires-Dist: hatch-vcs>=0.4.0; extra == 'dev'
Requires-Dist: hatch>=1.14.0; extra == 'dev'
Requires-Dist: hatchling>=1.27.0; extra == 'dev'
Requires-Dist: http-types; extra == 'dev'
Requires-Dist: json-types; extra == 'dev'
Requires-Dist: litellm-types; extra == 'dev'
Requires-Dist: mypy-boto3-s3<=1.36.21; extra == 'dev'
Requires-Dist: mypy-boto3-sts<=1.36.0; extra == 'dev'
Requires-Dist: mypy>=1.15.0; extra == 'dev'
Requires-Dist: pre-commit>=4.1.0; extra == 'dev'
Requires-Dist: pyupgrade>=3.19.1; extra == 'dev'
Requires-Dist: ruff>=0.9.6; extra == 'dev'
Requires-Dist: types-aioboto3; extra == 'dev'
Requires-Dist: types-aiobotocore; extra == 'dev'
Requires-Dist: types-aiofiles; extra == 'dev'
Requires-Dist: types-attrs; extra == 'dev'
Requires-Dist: types-awscrt>=0.23.10; extra == 'dev'
Requires-Dist: types-backports; extra == 'dev'
Requires-Dist: types-beautifulsoup4; extra == 'dev'
Requires-Dist: types-boto3>=1.36.22; extra == 'dev'
Requires-Dist: types-botocore; extra == 'dev'
Requires-Dist: types-cachetools; extra == 'dev'
Requires-Dist: types-jinja2; extra == 'dev'
Requires-Dist: types-lxml; extra == 'dev'
Requires-Dist: types-markdown; extra == 'dev'
Requires-Dist: types-pyyaml; extra == 'dev'
Requires-Dist: types-regex; extra == 'dev'
Requires-Dist: types-s3transfer>=0.11.2; extra == 'dev'
Requires-Dist: types-toml; extra == 'dev'
Requires-Dist: types-tqdm; extra == 'dev'
Provides-Extra: dropbox
Requires-Dist: dropbox>=12.00.2; extra == 'dropbox'
Provides-Extra: fal
Requires-Dist: fal-client>=0.5.9; extra == 'fal'
Provides-Extra: s3
Requires-Dist: boto3>=1.36.22; extra == 's3'
Requires-Dist: botocore>=1.36.22; extra == 's3'
Provides-Extra: test
Requires-Dist: pytest-asyncio>=0.25.3; extra == 'test'
Requires-Dist: pytest-benchmark>=5.1.0; extra == 'test'
Requires-Dist: pytest-cov>=6.0.0; extra == 'test'
Requires-Dist: pytest-mock>=3.14.0; extra == 'test'
Requires-Dist: pytest-timeout>=2.3.1; extra == 'test'
Requires-Dist: pytest>=8.3.4; extra == 'test'
